odoo/addons/delivery_sending/README.rst
odoo/addons/delivery_sending/__init__.py
odoo/addons/delivery_sending/__manifest__.py
odoo/addons/delivery_sending/api/ws_clientes.wsdl.xml
odoo/addons/delivery_sending/i18n/delivery_sending.pot
odoo/addons/delivery_sending/i18n/es.po
odoo/addons/delivery_sending/models/__init__.py
odoo/addons/delivery_sending/models/delivery_carrier.py
odoo/addons/delivery_sending/models/product_packaging.py
odoo/addons/delivery_sending/models/sending_master_data.py
odoo/addons/delivery_sending/models/sending_request.py
odoo/addons/delivery_sending/models/stock_picking.py
odoo/addons/delivery_sending/readme/CONFIGURE.rst
odoo/addons/delivery_sending/readme/CONTRIBUTORS.rst
odoo/addons/delivery_sending/readme/DESCRIPTION.rst
odoo/addons/delivery_sending/readme/INSTALL.rst
odoo/addons/delivery_sending/readme/ROADMAP.rst
odoo/addons/delivery_sending/readme/USAGE.rst
odoo/addons/delivery_sending/static/description/icon.png
odoo/addons/delivery_sending/static/description/index.html
odoo/addons/delivery_sending/tests/__init__.py
odoo/addons/delivery_sending/tests/test_delivery_sending.py
odoo/addons/delivery_sending/views/delivery_sending_view.xml
odoo/addons/delivery_sending/views/stock_picking_views.xml
odoo13_addon_delivery_sending-13.0.1.2.1.dist-info/METADATA
odoo13_addon_delivery_sending-13.0.1.2.1.dist-info/WHEEL
odoo13_addon_delivery_sending-13.0.1.2.1.dist-info/top_level.txt
odoo13_addon_delivery_sending-13.0.1.2.1.dist-info/RECORD
