Metadata-Version: 2.1
Name: odoo13-addon-delivery-sending
Version: 13.0.1.2.1
Summary: Delivery Carrier implementation for Sending API
Home-page: https://github.com/OCA/delivery-carrier
Author: Impulso Diagonal, Tecnativa, Odoo Community Association (OCA)
Author-email: support@odoo-community.org
License: AGPL-3
Platform: UNKNOWN
Classifier: Programming Language :: Python
Classifier: Framework :: Odoo
Classifier: Framework :: Odoo :: 13.0
Classifier: License :: OSI Approved :: GNU Affero General Public License v3
Requires-Python: >=3.5
Requires-Dist: odoo13-addon-delivery-package-number
Requires-Dist: odoo13-addon-delivery-state
Requires-Dist: odoo (<13.1dev,>=13.0a)
Requires-Dist: suds-jurko
